README.md
setup.py
anonymize/__init__.py
anonymize/main.py
anonymize/core/__init__.py
anonymize/core/completer.py
anonymize/core/hostname.py
anonymize/core/mac_address.py
anonymize/core/preference.py
anonymize/core/virtual_private_network.py
completion/anonymize
data/mac_address
doc/anonymize.1.gz
pkg_anonymize.egg-info/PKG-INFO
pkg_anonymize.egg-info/SOURCES.txt
pkg_anonymize.egg-info/dependency_links.txt
pkg_anonymize.egg-info/entry_points.txt
pkg_anonymize.egg-info/top_level.txt
service/anonymize.service