Metadata-Version: 1.1
Name: pkg-anonymize
Version: 0.0.3
Summary: A program that help to protect your privacy against global mass surveillance and been secure on the web.
Home-page: https://github.com/lognoz/anonymize
Author: Marc-Antoine Loignon
Author-email: info@lognoz.com
License: BSD
Platform: Linux
Classifier: License :: OSI Approved :: BSD License
Classifier: Programming Language :: Python :: 2.7
Classifier: Programming Language :: Python :: 3
Classifier: Programming Language :: Python :: 3.4
Classifier: Programming Language :: Python :: 3.5
Classifier: Programming Language :: Python :: 3.6
